thormang/__init__.py
thormang/envs/__init__.py
thormang/envs/thormang_env.py
thormang-0.0.1.dist-info/METADATA
thormang-0.0.1.dist-info/WHEEL
thormang-0.0.1.dist-info/top_level.txt
thormang-0.0.1.dist-info/RECORD
