Metadata-Version: 2.1
Name: thormang
Version: 0.0.1
Summary: A OpenAI Gym Env for thormang
Home-page: UNKNOWN
License: UNKNOWN
Platform: UNKNOWN
Requires-Dist: gym
